[{"formats":["https:\/\/www.rijksmuseum.nl\/assetimage2.jsp?id=AK-MAK-197","https:\/\/www.rijksmuseum.nl\/nl\/collectie\/AK-MAK-197","hoogte 7.5 CMcmcm","materiaal: brons","materiaal: verguldsel","materiaal: turkoois","techniek: vergulden"],"identifier":"RM0001.COLLECT.2261","language":"Dutch","publisher":"Rijksmuseum","rights":"http:\/\/creativecommons.org\/publicdomain\/zero\/1.0\/","date":"1700 -  1800","description":"Groene Tara, zittend, rechterbeen hangt naar beneden en steunt op een lotus.","creator":" : anoniem","coverage":"18e eeuw","type":"beeld","title":"Tara","contributor":"Bruikleen van de Vereniging van Vrienden der Aziatische Kunst"},{"formats":["https:\/\/www.rijksmuseum.nl\/assetimage2.jsp?id=AK-MAK-98","https:\/\/www.rijksmuseum.nl\/nl\/collectie\/AK-MAK-98","schildering: hoogte 123 CMcmcm","schildering: breedte 58 CMcmcm","montering: hoogte  ","montering: breedte 67.4 CMcmcm","mont. + rolstok: breedte 685 MMmmmm","rol: diameter 46 MMmmmm","rolstok: diameter 30 MMmmmm","materiaal: inkt","materiaal: papier"],"identifier":"RM0001.COLLECT.2262","language":"Dutch","publisher":"Rijksmuseum","rights":"http:\/\/creativecommons.org\/publicdomain\/zero\/1.0\/","date":"1800 -  1825","description":"Schildering voorstellende bamboe. Gesigneerd Shaoxiang (volgeling van Cheng Pan-chiao)","creator":" schilder: Shiao-hsiang","coverage":"eerste kwart 19e eeuw","type":"schildering","title":"Schildering met bamboe","contributor":"Bruikleen van de Vereniging van Vrienden der Aziatische Kunst"},{"formats":["https:\/\/www.rijksmuseum.nl\/assetimage2.jsp?id=AK-MAK-178","https:\/\/www.rijksmuseum.nl\/nl\/collectie\/AK-MAK-178","hoogte 34.0 CMcmcm","breedte 49.5 CMcmcm","diepte 27.5 CMcmcm","materiaal: hout","materiaal: lak","materiaal: parelmoer","materiaal: metaaldraad"],"identifier":"RM0001.COLLECT.2263","language":"Dutch","publisher":"Rijksmuseum","rights":"http:\/\/creativecommons.org\/publicdomain\/zero\/1.0\/","date":"1200 -  1300","description":"Kist voor het bewaren van Sutra`s.","creator":" : anoniem","coverage":"13e eeuw","type":"doos","title":"Sutradoos","contributor":"Bruikleen van de Vereniging van Vrienden der Aziatische Kunst"},{"formats":["https:\/\/www.rijksmuseum.nl\/assetimage2.jsp?id=AK-MAK-552","https:\/\/www.rijksmuseum.nl\/nl\/collectie\/AK-MAK-552","hoogte 10.5 CMcmcm","breedte 34.5 CMcmcm","diepte 19.5 CMcmcm","materiaal: lak","materiaal: parelmoer"],"identifier":"RM0001.COLLECT.2266","language":"Dutch","publisher":"Rijksmuseum","rights":"http:\/\/creativecommons.org\/publicdomain\/zero\/1.0\/","date":"1300 -  1500","description":"Lakdoos.","creator":" : anoniem","coverage":"15e eeuw","type":"doos","title":"Lakdoos","contributor":"Bruikleen van de Vereniging van Vrienden der Aziatische Kunst"},{"formats":["https:\/\/www.rijksmuseum.nl\/assetimage2.jsp?id=AK-MAK-584","https:\/\/www.rijksmuseum.nl\/nl\/collectie\/AK-MAK-584","hoogte 9.5 CMcmcm","diameter 19.0 CMcmcm","materiaal: brons"],"identifier":"RM0001.COLLECT.2267","language":"Dutch","publisher":"Rijksmuseum","rights":"http:\/\/creativecommons.org\/publicdomain\/zero\/1.0\/","date":"1300 -  1600","description":"Doos","creator":" : anoniem","coverage":"16e eeuw","type":"doos","title":"Metalen dekseldoos","contributor":"Bruikleen van de Vereniging van Vrienden der Aziatische Kunst"},{"formats":["https:\/\/www.rijksmuseum.nl\/assetimage2.jsp?id=AK-MAK-551","https:\/\/www.rijksmuseum.nl\/nl\/collectie\/AK-MAK-551","hoogte 22.0 CMcmcm","diameter 24.0 CMcmcm","materiaal: steengoed"],"identifier":"RM0001.COLLECT.2271","language":"Dutch","publisher":"Rijksmuseum","rights":"http:\/\/creativecommons.org\/publicdomain\/zero\/1.0\/","date":"ca. 1600 - ca. 1699","description":"Pot, onderglazuur koper-rood, versiering van druiven en ranken.","creator":" : anoniem","coverage":"17e eeuw","type":"pot","title":"Pot met onderglazuur decoratie in koperrood van druiven en ranken.","contributor":"Bruikleen van de Vereniging van Vrienden der Aziatische Kunst"},{"formats":["https:\/\/www.rijksmuseum.nl\/assetimage2.jsp?id=AK-MAK-590","https:\/\/www.rijksmuseum.nl\/nl\/collectie\/AK-MAK-590","hoogte 34.0 CMcmcm","breedte 20.0 CMcmcm","materiaal: celadon","materiaal: glazuur","materiaal: goudlak"],"identifier":"RM0001.COLLECT.2273","language":"Dutch","publisher":"Rijksmuseum","rights":"http:\/\/creativecommons.org\/publicdomain\/zero\/1.0\/","date":"918 -  1392","description":"Fles met ingelegd celadon-glazuur, met goudlak reparaturen.","creator":" : anoniem","coverage":"14e eeuw","type":"fles","title":"Fles met ingelegd celadon-glazuur","subject":"Iconclasscode: 48A9831","contributor":"Bruikleen van de Vereniging van Vrienden der Aziatische Kunst"},{"formats":["https:\/\/www.rijksmuseum.nl\/assetimage2.jsp?id=AK-MAK-637","https:\/\/www.rijksmuseum.nl\/nl\/collectie\/AK-MAK-637","diameter 12.8 CMcmcm","materiaal: aardewerk","materiaal: glazuur"],"identifier":"RM0001.COLLECT.2281","language":"Dutch","publisher":"Rijksmuseum","rights":"http:\/\/creativecommons.org\/publicdomain\/zero\/1.0\/","date":"1600 -  1699","description":"Theekom, goudlak reparaturen. Cr\u00e8me-kleurig glazuur.","creator":" : anoniem","coverage":"17e eeuw","type":"theekom","contributor":"Bruikleen van de Vereniging van Vrienden der Aziatische Kunst"},{"formats":["https:\/\/www.rijksmuseum.nl\/assetimage2.jsp?id=AK-MAK-640","https:\/\/www.rijksmuseum.nl\/nl\/collectie\/AK-MAK-640","hoogte 11 CMcmcm","materiaal: aardewerk","materiaal: glazuur"],"identifier":"RM0001.COLLECT.2284","language":"Dutch","publisher":"Rijksmuseum","rights":"http:\/\/creativecommons.org\/publicdomain\/zero\/1.0\/","date":"1700 -  1799","description":"Pot, dikke cr\u00eame-glazuur.","creator":" : ","coverage":"18e eeuw","type":"pot","contributor":"Bruikleen van de Vereniging van Vrienden der Aziatische Kunst"},{"formats":["https:\/\/www.rijksmuseum.nl\/assetimage2.jsp?id=RP-T-1945-20","https:\/\/www.rijksmuseum.nl\/nl\/collectie\/RP-T-1945-20","hoogte 187 MMmmmm","breedte 317 MMmmmm","materiaal: papier","techniek: zwart krijt"],"identifier":"RM0001.COLLECT.2292","language":"Dutch","publisher":"Rijksmuseum","rights":"http:\/\/creativecommons.org\/publicdomain\/zero\/1.0\/","date":"1738 -  1806","description":"Landelijke behuizing in bosrijke omgeving; op de voorgrond spelen enige mannen een kegelspel.","creator":" tekenaar: Pillement, Jean Baptiste","coverage":"eerste kwart 19e eeuw","type":"tekening","title":"Landelijke behuizing in bosrijke omgeving"}]